firefly_di/__init__.py
firefly_dependency_injection-1.0.0.dist-info/LICENSE
firefly_dependency_injection-1.0.0.dist-info/METADATA
firefly_dependency_injection-1.0.0.dist-info/WHEEL
firefly_dependency_injection-1.0.0.dist-info/top_level.txt
firefly_dependency_injection-1.0.0.dist-info/RECORD
